nondb/NonDB.py
nondb/NonIndex.py
nondb/NonTable.py
nondb/Storage.py
nondb/__init__.py
nondb-0.1.4.dist-info/WHEEL
nondb-0.1.4.dist-info/METADATA
nondb-0.1.4.dist-info/RECORD
