Metadata-Version: 2.3
Name: nondb
Version: 0.1.4
Summary: A document store for Pydantic models
Author: slank
Author-email: slank <slank@smacky.org>
License: MIT
Requires-Dist: jmespath>=1.0.1
Requires-Dist: pydantic>=2.11.7
Requires-Python: >=3.12
Project-URL: Homepage, https://github.com/slank/nondb
Project-URL: Repository, https://github.com/slank/nondb.git
